jaffadata/__init__.py
jaffadata/core/dataset.py
jaffadata/core/labels.py
jaffadata/core/mask.py
jaffadata/datasets/__init__.py
jaffadata/datasets/arca23k.py
jaffadata/datasets/audioset.py
jaffadata/datasets/esc.py
jaffadata/datasets/fsd50k.py
jaffadata/datasets/fsdkaggle2018.py
jaffadata/datasets/fsdkaggle2019.py
jaffadata/datasets/fsdnoisy18k.py
jaffadata/datasets/tau_nigens.py
jaffadata/datasets/urbansound.py
jaffadata-0.3.1.dist-info/LICENSE
jaffadata-0.3.1.dist-info/WHEEL
jaffadata-0.3.1.dist-info/METADATA
jaffadata-0.3.1.dist-info/RECORD
