Metadata-Version: 2.1
Name: jaffadata
Version: 0.3.1
Summary: A library for working with audio datasets in ML
Home-page: https://github.com/tqbl/jaffadata
License: ISC
Author: Turab Iqbal
Author-email: t.iqbal@surrey.ac.uk
Requires-Python: >=3.8,<3.11
Classifier: Intended Audience :: Developers
Classifier: Intended Audience :: Science/Research
Classifier: License :: OSI Approved
Classifier: Programming Language :: Python :: 3
Classifier: Programming Language :: Python :: 3.10
Classifier: Programming Language :: Python :: 3.8
Classifier: Programming Language :: Python :: 3.9
Classifier: Topic :: Scientific/Engineering
Classifier: Topic :: Software Development
Classifier: Topic :: Software Development :: Libraries
Classifier: Topic :: Software Development :: Libraries :: Python Modules
Requires-Dist: numpy (>=1.21.3,<2.0.0)
Requires-Dist: pandas (>=1.3.4,<2.0.0)
Project-URL: Repository, https://github.com/tqbl/jaffadata
